sincomp/__init__.py
sincomp/align.py
sincomp/auxiliary.py
sincomp/ccr_char_info.csv
sincomp/ccr_dialect_info.csv
sincomp/compare.py
sincomp/datasets.py
sincomp/models.py
sincomp/preprocess.py
sincomp/similarity.py
sincomp/plot/__init__.py
sincomp/plot/geography.py
sincomp-0.2.0.dist-info/licenses/LICENSE
sincomp-0.2.0.dist-info/METADATA
sincomp-0.2.0.dist-info/WHEEL
sincomp-0.2.0.dist-info/top_level.txt
sincomp-0.2.0.dist-info/RECORD
