Metadata-Version: 2.4
Name: sincomp
Version: 0.2.0
Summary: A toolset for computation and comparison of Chinese dialects
Author-email: 黄艺华 <lernanto@foxmail.com>
Project-URL: Homepage, https://github.com/lernanto/sincomp
Project-URL: Issues, https://github.com/lernanto/sincomp/issues
Classifier: Programming Language :: Python :: 3
Classifier: License :: OSI Approved :: MIT License
Classifier: Operating System :: OS Independent
Requires-Python: >=3.10
License-File: LICENSE
Requires-Dist: OpenCC
Requires-Dist: numpy
Requires-Dist: pandas[excel]>=1.5
Requires-Dist: retry
Requires-Dist: scipy
Requires-Dist: scikit-learn>=1.2
Provides-Extra: models
Requires-Dist: tensorflow>=2.8; extra == "models"
Provides-Extra: parser
Requires-Dist: sklearn-crfsuite; extra == "parser"
Provides-Extra: plot
Requires-Dist: cartopy; extra == "plot"
Requires-Dist: folium; extra == "plot"
Requires-Dist: geopandas; extra == "plot"
Requires-Dist: matplotlib; extra == "plot"
Requires-Dist: plotly; extra == "plot"
Requires-Dist: seaborn; extra == "plot"
Provides-Extra: test
Requires-Dist: sincomp[models,parser,plot]; extra == "test"
Dynamic: license-file
